inkBoard/__init__.py
inkBoard/__main__.py
inkBoard/arguments.py
inkBoard/bootstrap.py
inkBoard/constants.py
inkBoard/helpers.py
inkBoard/loaders.py
inkBoard/logging.py
inkBoard/packaging.py
inkBoard/types.py
inkBoard/configuration/__init__.py
inkBoard/configuration/configure.py
inkBoard/configuration/const.py
inkBoard/configuration/loaders.py
inkBoard/configuration/types.py
inkBoard/core/__init__.py
inkBoard/core/util.py
inkBoard/dashboard/__init__.py
inkBoard/dashboard/loader.py
inkBoard/dashboard/validate.py
inkBoard/files/icons/inkboard.ico
inkBoard/files/icons/inkboard_black.ico
inkBoard/files/images/default_background.png
inkBoard/files/images/logo.png
inkBoard/integrations/__init__.py
inkBoard/platforms/__init__.py
inkBoard/platforms/basedevice.py
inkBoard/platforms/validate.py
inkBoard-0.3.0.dist-info/LICENSE
inkBoard-0.3.0.dist-info/METADATA
inkBoard-0.3.0.dist-info/WHEEL
inkBoard-0.3.0.dist-info/entry_points.txt
inkBoard-0.3.0.dist-info/top_level.txt
inkBoard-0.3.0.dist-info/RECORD
