Metadata-Version: 2.2
Name: inkBoard
Version: 0.3.0
Summary: inkBoard aims to provide PSSM based dashboards in an easy, but flexible way
Author: Slalamander
License:                     GNU GENERAL PUBLIC LICENSE
Project-URL: Homepage, https://github.com/Slalamander/inkBoard
Project-URL: source, https://github.com/Slalamander/inkBoard
Keywords: gui,pixels,interface,MaterialDesignIcon,mdi icons,dashboards,dashboarding
Classifier: Programming Language :: Python :: 3.9
Classifier: Programming Language :: Python :: 3.10
Classifier: Operating System :: OS Independent
Classifier: License :: OSI Approved :: GNU General Public License v3 (GPLv3)
Requires-Python: >=3.9
License-File: LICENSE
Requires-Dist: PyYAML
Requires-Dist: PythonScreenStackManager>=0.3.6
